setup.py
strandex/__init__.py
strandex.egg-info/PKG-INFO
strandex.egg-info/SOURCES.txt
strandex.egg-info/dependency_links.txt
strandex.egg-info/entry_points.txt
strandex.egg-info/requires.txt
strandex.egg-info/top_level.txt