Metadata-Version: 1.0
Name: strandex
Version: 0.3.2
Summary: Strand-anchored regex for expansion or contraction of FASTQ files
Home-page: https://github.com/mdshw5/strandex
Author: Matthew Shirley
Author-email: mdshw5@gmail.com
License: MIT
Platform: UNKNOWN
Classifier: Development Status :: 3 - Alpha
Classifier: License :: OSI Approved :: MIT License
Classifier: Environment :: Console
Classifier: Intended Audience :: Science/Research
Classifier: Natural Language :: English
Classifier: Operating System :: Unix
Classifier: Programming Language :: Python :: 2.6
Classifier: Programming Language :: Python :: 2.7
Classifier: Programming Language :: Python :: 3.5
Classifier: Topic :: Scientific/Engineering :: Bio-Informatics
